consensus_entropy/__init__.py
consensus_entropy/core.py
consensus_entropy-0.1.0.dist-info/LICENSE
consensus_entropy-0.1.0.dist-info/METADATA
consensus_entropy-0.1.0.dist-info/WHEEL
consensus_entropy-0.1.0.dist-info/top_level.txt
consensus_entropy-0.1.0.dist-info/RECORD
