Metadata-Version: 2.2
Name: consensus-entropy
Version: 0.1.0
Summary: A library for calculating consensus entropy between multiple strings, particularly useful for OCR result analysis
Home-page: https://github.com/aslan.mingye@qq.com/consensus-entropy
Author: Yulong Zhang
Author-email: aslan.mingye@qq.com
Project-URL: Bug Tracker, https://github.com/aslan.mingye@qq.com/consensus-entropy/issues
Project-URL: Documentation, https://github.com/aslan.mingye@qq.com/consensus-entropy#readme
Project-URL: Source Code, https://github.com/aslan.mingye@qq.com/consensus-entropy
Project-URL: Paper, https://arxiv.org/abs/2504.11101
Keywords: ocr,entropy,consensus,text-processing,computer-vision,machine-learning
Classifier: Development Status :: 4 - Beta
Classifier: Intended Audience :: Science/Research
Classifier: License :: OSI Approved :: MIT License
Classifier: Operating System :: OS Independent
Classifier: Programming Language :: Python :: 3
Classifier: Programming Language :: Python :: 3.7
Classifier: Programming Language :: Python :: 3.8
Classifier: Programming Language :: Python :: 3.9
Classifier: Programming Language :: Python :: 3.10
Classifier: Programming Language :: Python :: 3.11
Classifier: Programming Language :: Python :: 3.12
Classifier: Topic :: Scientific/Engineering
Classifier: Topic :: Scientific/Engineering :: Artificial Intelligence
Classifier: Topic :: Text Processing
Classifier: Topic :: Text Processing :: General
Requires-Python: >=3.7
License-File: LICENSE
Requires-Dist: numpy>=1.19.0
Requires-Dist: python-Levenshtein>=0.12.0
Dynamic: author
Dynamic: author-email
Dynamic: classifier
Dynamic: description
Dynamic: description-content-type
Dynamic: home-page
Dynamic: keywords
Dynamic: project-url
Dynamic: requires-dist
Dynamic: requires-python
Dynamic: summary
